[
  {
    "id": 1,
    "author": "George R. R. Martin",
    "isbn": 9780553103540,
    "title": "A Game of Thrones",
    "publication_year": 1996,
    "created_at": "2024-04-25 16:52:33.098534+00"
  },
  {
    "id": 2,
    "author": "J. K. Rowling",
    "isbn": 9780747532743,
    "title": "Harry Potter and the Philosopher's Stone",
    "publication_year": 1997,
    "created_at": "2024-04-25 16:52:33.098534+00"
  },
  {
    "id": 3,
    "author": "J. R. R. Tolkien",
    "isbn": 9780618640157,
    "title": "The Lord of the Rings",
    "publication_year": 1954,
    "created_at": "2024-04-25 16:52:33.098534+00"
  }
]